pydwrap/__init__.py
pydwrap/main.py
pydwrap-0.6.0.dist-info/LICENSE
pydwrap-0.6.0.dist-info/METADATA
pydwrap-0.6.0.dist-info/WHEEL
pydwrap-0.6.0.dist-info/RECORD
