Metadata-Version: 2.1
Name: pydwrap
Version: 0.6.0
Summary: pydwrap stores a Option type to implement unpacking of values if they are not None. The BaseModel is also a little extended to work with the Option type.
Home-page: https://github.com/luwqz1/pydwrap
License: MIT
Keywords: python,wrapping,optional handle,basemodel fields,option,pydwrap
Author: Georgy howl
Author-email: howluwqz1@gmail.com
Requires-Python: >=3.9,<4.0
Classifier: Framework :: Pydantic
Classifier: License :: OSI Approved :: MIT License
Classifier: Programming Language :: Python :: 3
Classifier: Programming Language :: Python :: 3.9
Classifier: Programming Language :: Python :: 3.10
Classifier: Programming Language :: Python :: 3.11
Classifier: Programming Language :: Python :: 3 :: Only
Classifier: Topic :: Internet
Classifier: Topic :: Software Development :: Libraries :: Python Modules
Classifier: Typing :: Typed
Requires-Dist: pydantic (>=1.9.0,<2.0.0)
Project-URL: Repository, https://github.com/luwqz1/pydwrap
